LICENSE
README.md
pyproject.toml
setup.py
src/cocotb_AHB/__init__.py
src/cocotb_AHB/_version.py
src/cocotb_AHB.egg-info/PKG-INFO
src/cocotb_AHB.egg-info/SOURCES.txt
src/cocotb_AHB.egg-info/dependency_links.txt
src/cocotb_AHB.egg-info/requires.txt
src/cocotb_AHB.egg-info/top_level.txt
src/cocotb_AHB/AHB_common/AHB_types.py
src/cocotb_AHB/AHB_common/InterconnectInterface.py
src/cocotb_AHB/AHB_common/ManagerInterface.py
src/cocotb_AHB/AHB_common/MemoryInterface.py
src/cocotb_AHB/AHB_common/MonitorInterface.py
src/cocotb_AHB/AHB_common/MonitorableInterface.py
src/cocotb_AHB/AHB_common/SimulationInterface.py
src/cocotb_AHB/AHB_common/SubordinateInterface.py
src/cocotb_AHB/AHB_common/__init__.py
src/cocotb_AHB/drivers/DutManager.py
src/cocotb_AHB/drivers/DutSubordinate.py
src/cocotb_AHB/drivers/SimCmdExecAndCheck.py
src/cocotb_AHB/drivers/SimDefaultSubordinate.py
src/cocotb_AHB/drivers/SimMem1PSubordinate.py
src/cocotb_AHB/drivers/SimSimpleManager.py
src/cocotb_AHB/drivers/SimTrafficGenerator.py
src/cocotb_AHB/drivers/SimTrafficTester.py
src/cocotb_AHB/drivers/__init__.py
src/cocotb_AHB/interconnect/SimInterconnect.py
src/cocotb_AHB/interconnect/__init__.py
src/cocotb_AHB/monitors/AHBPacketMonitor.py
src/cocotb_AHB/monitors/AHBSignalMonitor.py
src/cocotb_AHB/monitors/__init__.py