Metadata-Version: 2.1
Name: cocotb-AHB
Version: 0.2.0
Summary: AHB cocotb drivers
Home-page: UNKNOWN
Author: Antmicro
License: Apache-2.0
Platform: UNKNOWN
Requires-Python: >=3.5
License-File: LICENSE
